bootstrap_difflib/__init__.py
bootstrap_difflib/bootstrap_difflib.py
bootstrap_difflib/utils.py
demo/__init__.py
demo/demo.py
tests/__init__.py
tests/test_bootstrap_difflib.py
bootstrap_difflib-0.0.3.dist-info/LICENSE
bootstrap_difflib-0.0.3.dist-info/METADATA
bootstrap_difflib-0.0.3.dist-info/WHEEL
bootstrap_difflib-0.0.3.dist-info/top_level.txt
bootstrap_difflib-0.0.3.dist-info/RECORD
