Metadata-Version: 2.1
Name: bootstrap-difflib
Version: 0.0.3
Summary: Making the output of DiffLib Bootstrap compatible
Home-page: https://github.com/tdjholder/bootstrap-difflib
Author: Thomas Holder
Author-email: tdjholder@gmail.com
License: UNKNOWN
Platform: UNKNOWN
Classifier: Programming Language :: Python :: 3
Classifier: License :: OSI Approved :: MIT License
Classifier: Operating System :: OS Independent
